tantipy/__init__.py
tantipy/tantivy_coder.py
tantipy/tantivy_reader.py
tantipy-0.1.2.dist-info/LICENSE
tantipy-0.1.2.dist-info/METADATA
tantipy-0.1.2.dist-info/WHEEL
tantipy-0.1.2.dist-info/top_level.txt
tantipy-0.1.2.dist-info/RECORD
