Metadata-Version: 2.1
Name: tantipy
Version: 0.1.2
Summary: UNKNOWN
Home-page: https://github.com/izihawa/tantipy
Author: Pasha Podolsky
License: MIT
Platform: UNKNOWN
Classifier: Topic :: Database :: Database Engines/Servers
Classifier: Topic :: Internet :: WWW/HTTP :: Indexing/Search
Classifier: Topic :: Utilities
Requires-Dist: brotli (>=1.0.9)
Requires-Dist: izihawa-types (>=0.1.0)
